{
  "projects": [
    {
      "id": "3a0d",
      "name": "Ygao",
      "budget": "1222",
      "category": {
        "id": "2",
        "name": "Desenvolvimento"
      },
      "cost": 0,
      "services": []
    },
    {
      "id": "f4e8",
      "name": "Ygao",
      "budget": "1222",
      "category": {
        "id": "2",
        "name": "Desenvolvimento"
      },
      "cost": 0,
      "services": []
    },
    {
      "id": "c910",
      "name": "Ygor",
      "budget": "1111",
      "category": {
        "id": "2",
        "name": "Desenvolvimento"
      },
      "cost": 0,
      "services": []
    },
    {
      "id": "85af",
      "name": "Ygao",
      "budget": "20000",
      "category": {
        "id": "2",
        "name": "Desenvolvimento"
      },
      "cost": 0,
      "services": []
    },
    {
      "id": "405f",
      "name": "Pedro",
      "budget": "11111",
      "category": {
        "id": "1",
        "name": "Infra"
      },
      "cost": 0,
      "services": []
    },
    {
      "id": "3b32",
      "name": "Pedro",
      "budget": "111111",
      "category": {
        "id": "1",
        "name": "Infra"
      },
      "cost": 0,
      "services": []
    }
  ],
  "categories": [
    {
      "id": "1",
      "name": "Infra"
    },
    {
      "id": "2",
      "name": "Desenvolvimento"
    },
    {
      "id": "3",
      "name": "Design"
    },
    {
      "id": "4",
      "name": "Planejamento"
    }
  ]
}